csbdeep/__init__.py
csbdeep/version.py
csbdeep/data/__init__.py
csbdeep/data/generate.py
csbdeep/data/prepare.py
csbdeep/data/rawdata.py
csbdeep/data/transform.py
csbdeep/internals/__init__.py
csbdeep/internals/blocks.py
csbdeep/internals/losses.py
csbdeep/internals/nets.py
csbdeep/internals/predict.py
csbdeep/internals/probability.py
csbdeep/internals/train.py
csbdeep/io/__init__.py
csbdeep/models/__init__.py
csbdeep/models/base_model.py
csbdeep/models/care_isotropic.py
csbdeep/models/care_projection.py
csbdeep/models/care_standard.py
csbdeep/models/care_upsampling.py
csbdeep/models/config.py
csbdeep/models/pretrained.py
csbdeep/scripts/__init__.py
csbdeep/scripts/care_predict.py
csbdeep/utils/__init__.py
csbdeep/utils/plot_utils.py
csbdeep/utils/six.py
csbdeep/utils/tf.py
csbdeep/utils/utils.py
csbdeep-0.8.2.dist-info/LICENSE.txt
csbdeep-0.8.2.dist-info/METADATA
csbdeep-0.8.2.dist-info/WHEEL
csbdeep-0.8.2.dist-info/entry_points.txt
csbdeep-0.8.2.dist-info/top_level.txt
csbdeep-0.8.2.dist-info/RECORD
